labchain/simulator.py
labchain-0.0.1.dist-info/METADATA
labchain-0.0.1.dist-info/WHEEL
labchain-0.0.1.dist-info/top_level.txt
labchain-0.0.1.dist-info/RECORD
