Metadata-Version: 2.4
Name: labchain
Version: 0.0.1
Summary: Simulator of chemistry laboratory experiments
Author-email: Israel Neto <israneto20@gmail.com>
License: MIT
Classifier: Programming Language :: Python :: 3
Classifier: License :: OSI Approved :: MIT License
Classifier: Operating System :: OS Independent
Requires-Python: >=3.8
